uutils/__init__.py
uutils/data_process/__init__.py
uutils-0.0.3.dist-info/DESCRIPTION.rst
uutils-0.0.3.dist-info/METADATA
uutils-0.0.3.dist-info/RECORD
uutils-0.0.3.dist-info/WHEEL
uutils-0.0.3.dist-info/metadata.json
uutils-0.0.3.dist-info/top_level.txt
