Metadata-Version: 2.0
Name: uutils
Version: 0.0.3
Summary: uutils
Home-page: https://github.com/CzKerwin/uutils.git
Author: CzKerwin
Author-email: czksnk@outlook.com
License: MIT Licence
Platform: any
Requires-Python: >=3.5
